README.txt
setup.cfg
setup.py
frankAllSkyCam/__init__.py
frankAllSkyCam/__main__.py
frankAllSkyCam/allskycamdelete.py
frankAllSkyCam/config.py
frankAllSkyCam/crontab.py
frankAllSkyCam/drawtext.py
frankAllSkyCam/exposurecalc.py
frankAllSkyCam/fileManager.py
frankAllSkyCam/getextdata.py
frankAllSkyCam/imageHeader.py
frankAllSkyCam/index.py
frankAllSkyCam/logos.py
frankAllSkyCam/sqmexp.py
frankAllSkyCam/sqmreader.py
frankAllSkyCam/startrail.py
frankAllSkyCam/suncalc2.py
frankAllSkyCam/test_suncalc.py
frankAllSkyCam/timelapse.py
frankAllSkyCam/watchDog.py
frankAllSkyCam.egg-info/PKG-INFO
frankAllSkyCam.egg-info/SOURCES.txt
frankAllSkyCam.egg-info/dependency_links.txt
frankAllSkyCam.egg-info/requires.txt
frankAllSkyCam.egg-info/top_level.txt