Metadata-Version: 2.1
Name: frankAllSkyCam
Version: 8.4
Summary: AllSkyCamera with Raspberry Pi and Pi HQ Camera 
Home-page: https://github.com/sferlix/frankAllSkyCam
Download-URL: https://github.com/sferlix/frankAllSkyCam/archive/refs/tags/8.4.tar.gz
Author: Francesco Sferlazza
Author-email: sferlazza@gmail.com
License: MIT
Keywords: AllSkyCamera,Astronomy,AllSky
Classifier: Development Status :: 4 - Beta
Classifier: Intended Audience :: Developers
Classifier: Topic :: Software Development :: Build Tools
Classifier: License :: OSI Approved :: MIT License
Classifier: Programming Language :: Python :: 3
Classifier: Programming Language :: Python :: 3.4
Classifier: Programming Language :: Python :: 3.5
Classifier: Programming Language :: Python :: 3.6
Classifier: Programming Language :: Python :: 3.7
Classifier: Programming Language :: Python :: 3.9
